tjax/__init__.py
tjax/dataclasses.py
tjax/gradient.py
tjax/py.typed
tjax/_src/__init__.py
tjax/_src/abstract_method_decorators.py
tjax/_src/annotations.py
tjax/_src/cotangent_tools.py
tjax/_src/dtype_tools.py
tjax/_src/function_markers.py
tjax/_src/leaky_integral.py
tjax/_src/math_tools.py
tjax/_src/partial.py
tjax/_src/project_tree.py
tjax/_src/rng.py
tjax/_src/shims.py
tjax/_src/testing.py
tjax/_src/timer.py
tjax/_src/tree_tools.py
tjax/_src/dataclasses/__init__.py
tjax/_src/dataclasses/dataclass.py
tjax/_src/dataclasses/helpers.py
tjax/_src/display/__init__.py
tjax/_src/display/colors.py
tjax/_src/display/display_generic.py
tjax/_src/display/generic_string.py
tjax/_src/display/internal.py
tjax/_src/display/print_generic.py
tjax/_src/gradient/__init__.py
tjax/_src/gradient/aliases.py
tjax/_src/gradient/chain.py
tjax/_src/gradient/smd.py
tjax/_src/gradient/transform.py
tjax/_src/gradient/transforms.py
tjax/_src/graph/__init__.py
tjax/_src/graph/display.py
tjax/_src/graph/register_jax.py
tjax/_src/graph/types_.py
tjax-1.4.1.dist-info/METADATA
tjax-1.4.1.dist-info/WHEEL
tjax-1.4.1.dist-info/licenses/LICENSE
tjax-1.4.1.dist-info/RECORD
