Metadata-Version: 2.4
Name: tjax
Version: 1.4.1
Summary: Tools for JAX.
Project-URL: source, https://github.com/NeilGirdhar/tjax
Author: Neil Girdhar
Author-email: mistersheik@gmail.com
Maintainer: Neil Girdhar
Maintainer-email: mistersheik@gmail.com
License-Expression: Apache-2.0
License-File: LICENSE
Classifier: Development Status :: 4 - Beta
Classifier: Intended Audience :: Science/Research
Classifier: License :: OSI Approved :: Apache Software License
Classifier: Operating System :: OS Independent
Classifier: Programming Language :: Python
Classifier: Programming Language :: Python :: 3
Classifier: Programming Language :: Python :: 3.12
Classifier: Programming Language :: Python :: 3.13
Classifier: Programming Language :: Python :: 3.14
Classifier: Topic :: Scientific/Engineering :: Artificial Intelligence
Classifier: Topic :: Software Development :: Libraries :: Python Modules
Classifier: Topic :: Utilities
Classifier: Typing :: Typed
Requires-Python: <3.15,>=3.12
Requires-Dist: array-api-compat>=1.10
Requires-Dist: array-api-extra>=0.6.0
Requires-Dist: jax>=0.7
Requires-Dist: numpy>=1.25
Requires-Dist: optax>=0.2.3
Requires-Dist: optype[numpy]>=0.12.2
Requires-Dist: rich>=13.7
Requires-Dist: typing-extensions>=4.11
